home_run/__init__.py
home_run/base.py
home_run/keras.py
home_run/python.py
home_run/pytorch.py
home_run/sklearn.py
home_run/tensorflow.py
home_run/utils.py
home_run/version.py
home_run-0.5.0.dist-info/METADATA
home_run-0.5.0.dist-info/WHEEL
home_run-0.5.0.dist-info/top_level.txt
home_run-0.5.0.dist-info/RECORD
