Metadata-Version: 2.1
Name: home-run
Version: 0.5.0
Summary: Turns DLHub metadata into functional Python objects
Home-page: https://github.com/dlhub-argonne/home_run
Author: Ryan Chard
Author-email: rchard@anl.gov
License: Apache License, Version 2.0
Keywords: DLHub,Data and Learning Hub for Science,machine learning,data publication,software publication,reproducibility
Platform: UNKNOWN
Classifier: Development Status :: 3 - Alpha
Classifier: Intended Audience :: Developers
Classifier: License :: OSI Approved :: Apache Software License
Classifier: Programming Language :: Python
Classifier: Topic :: System :: Distributed Computing
Requires-Python: >=3.6
Requires-Dist: requests
